env_cmd.py
env_cmd-1.1.dist-info/METADATA
env_cmd-1.1.dist-info/RECORD
env_cmd-1.1.dist-info/WHEEL
env_cmd-1.1.dist-info/top_level.txt
