Metadata-Version: 2.1
Name: env-cmd
Version: 1.1
Summary: A simple wrapper for executing virtualenv commands and passing them environment variables via a config file.
Home-page: https://github.com/brutasse/env-cmd
Author: Bruno Renié
Author-email: UNKNOWN
License: BSD
Platform: any
Classifier: Intended Audience :: Developers
Classifier: Intended Audience :: System Administrators
Classifier: License :: OSI Approved :: BSD License
Classifier: Operating System :: OS Independent
Classifier: Programming Language :: Python
Classifier: Programming Language :: Python :: 3
